LICENSE
README.md
setup.py
SimpleAxel_Account.egg-info/PKG-INFO
SimpleAxel_Account.egg-info/SOURCES.txt
SimpleAxel_Account.egg-info/dependency_links.txt
SimpleAxel_Account.egg-info/top_level.txt
account/__init__.py
account/main.py